contxt/__init__.py
contxt/__main__.py
contxt/auth/__init__.py
contxt/auth/cli.py
contxt/auth/jwt.py
contxt/auth/machine.py
contxt/cli/clients.py
contxt/cli/commands/auth.py
contxt/cli/commands/clusters.py
contxt/cli/commands/edge_nodes.py
contxt/cli/commands/ems.py
contxt/cli/commands/facilities.py
contxt/cli/commands/iot.py
contxt/cli/commands/metrics.py
contxt/cli/commands/orgs.py
contxt/cli/commands/project_envs.py
contxt/cli/commands/projects.py
contxt/cli/commands/roles.py
contxt/cli/commands/service_instances.py
contxt/cli/commands/services.py
contxt/cli/log.py
contxt/cli/main.py
contxt/cli/utils.py
contxt/generated/nionic_queries.py
contxt/generated/nionic_schema.py
contxt/models/__init__.py
contxt/models/bus.py
contxt/models/contxt.py
contxt/models/ems.py
contxt/models/etl.py
contxt/models/events.py
contxt/models/iot.py
contxt/models/sis.py
contxt/py.typed
contxt/services/__init__.py
contxt/services/api.py
contxt/services/auth.py
contxt/services/bus.py
contxt/services/contxt.py
contxt/services/contxt_access.py
contxt/services/contxt_deployments.py
contxt/services/ems.py
contxt/services/events.py
contxt/services/iot.py
contxt/services/ngest.py
contxt/services/nionic.py
contxt/services/pagination.py
contxt/utils/__init__.py
contxt/utils/object_mapper.py
contxt/utils/serializer.py
contxt/workers.py
contxt_sdk-6.9.0.dist-info/METADATA
contxt_sdk-6.9.0.dist-info/WHEEL
contxt_sdk-6.9.0.dist-info/entry_points.txt
contxt_sdk-6.9.0.dist-info/licenses/LICENSE
contxt_sdk-6.9.0.dist-info/RECORD
