Metadata-Version: 2.4
Name: contxt-sdk
Version: 6.9.0
Summary: Contxt SDK from ndustrial
License: ISC
License-File: LICENSE
Author: ndustrial
Author-email: dev@ndustrial.io
Requires-Python: >=3.9.2,<4.0.0
Classifier: License :: OSI Approved
Classifier: Programming Language :: Python :: 3
Classifier: Programming Language :: Python :: 3.10
Classifier: Programming Language :: Python :: 3.11
Classifier: Programming Language :: Python :: 3.12
Classifier: Programming Language :: Python :: 3.13
Classifier: Programming Language :: Python :: 3.14
Provides-Extra: crypto
Requires-Dist: auth0-python (>=4,<5)
Requires-Dist: click (>=7,<9)
Requires-Dist: cryptography (>=42.0.4) ; extra == "crypto"
Requires-Dist: pyjwt (>=2,<3)
Requires-Dist: python-slugify (>=6.1.2,<9.0.0)
Requires-Dist: pyyaml (>=6.0.2,<7.0.0)
Requires-Dist: requests (>=2,<3)
Requires-Dist: sgqlc (>=15,<17)
Requires-Dist: tabulate
Project-URL: Repository, https://github.com/ndustrialio/contxt-sdk-python
